PySparkIP/AVL_Tree.py
PySparkIP/IPAddressUDT.py
PySparkIP/PySparkIP.py
PySparkIP/__init__.py
PySparkIP-1.1.9.dist-info/LICENSE
PySparkIP-1.1.9.dist-info/METADATA
PySparkIP-1.1.9.dist-info/WHEEL
PySparkIP-1.1.9.dist-info/top_level.txt
PySparkIP-1.1.9.dist-info/RECORD
