Metadata-Version: 2.1
Name: PySparkIP
Version: 1.1.9
Summary: An API for working with IP addresses in Apache Spark.
Home-page: https://github.com/jshalaby510/PySparkIP
Author: Julian Shalaby, Ryan Jacobs, Prateek Narayanan
Project-URL: Bug Tracker, https://github.com/jshalaby510/PySparkIP/issues
Classifier: Programming Language :: Python :: 3
Classifier: License :: OSI Approved :: Apache Software License
Classifier: Operating System :: OS Independent
Requires-Python: >=3.6
License-File: LICENSE
